SquidLibs/ErrorHandler.py
SquidLibs/FileHelper.py
SquidLibs/TranslationManager.py
SquidLibs/__init__.py
SquidLibs/windowMethods.py
SquidLibs/lang/Default/basics_translate.txt
SquidLibs-0.0.5.dist-info/LICENSE
SquidLibs-0.0.5.dist-info/METADATA
SquidLibs-0.0.5.dist-info/WHEEL
SquidLibs-0.0.5.dist-info/top_level.txt
SquidLibs-0.0.5.dist-info/RECORD
