Metadata-Version: 2.1
Name: SquidLibs
Version: 0.0.5
Summary: A Python library for translation, tkinter Windows, and basic file handling
Home-page: https://github.com/SquidCoderIndustries/SquidLibs
Author: Squid Coder
Author-email: squid@squidcoder.com
Classifier: Programming Language :: Python :: 3
Classifier: License :: OSI Approved :: GNU General Public License v3 (GPLv3)
Classifier: Operating System :: OS Independent
Requires-Python: >=3.6
License-File: LICENSE
